milliseconds/__about__.py
milliseconds/__init__.py
milliseconds/constants.py
milliseconds/milliseconds.py
milliseconds-0.1.2.dist-info/METADATA
milliseconds-0.1.2.dist-info/WHEEL
milliseconds-0.1.2.dist-info/licenses/LICENSE.txt
milliseconds-0.1.2.dist-info/RECORD
