Metadata-Version: 2.4
Name: milliseconds
Version: 0.1.2
Summary: Utility class for working with POSIX timestamps in milliseconds.
Project-URL: Documentation, https://github.com/traverne/milliseconds#readme
Project-URL: Issues, https://github.com/traverne/milliseconds/issues
Project-URL: Source, https://github.com/traverne/milliseconds
Author-email: Athen Traverne <athen@aetherionresearch.com>
License-Expression: MIT
License-File: LICENSE.txt
Classifier: Development Status :: 4 - Beta
Classifier: Programming Language :: Python
Classifier: Programming Language :: Python :: 3.9
Classifier: Programming Language :: Python :: 3.10
Classifier: Programming Language :: Python :: 3.11
Classifier: Programming Language :: Python :: 3.12
Classifier: Programming Language :: Python :: 3.13
Classifier: Programming Language :: Python :: 3.14
Classifier: Programming Language :: Python :: Implementation :: CPython
Classifier: Programming Language :: Python :: Implementation :: PyPy
Requires-Python: >=3.9
